{
  "main": {
    "id": "4a3055e1d988e1b4",
    "type": "split",
    "children": [
      {
        "id": "9b15287a3feb5a26",
        "type": "tabs",
        "children": [
          {
            "id": "5b4082abaec91411",
            "type": "leaf",
            "state": {
              "type": "markdown",
              "state": {
                "file": "20250623.md",
                "mode": "source",
                "source": false
              },
              "icon": "lucide-file",
              "title": "20250623"
            }
          }
        ]
      }
    ],
    "direction": "vertical"
  },
  "left": {
    "id": "ce6ec097536c41e9",
    "type": "split",
    "children": [
      {
        "id": "b5e59306ddd578a9",
        "type": "tabs",
        "children": [
          {
            "id": "375c909efd5a2366",
            "type": "leaf",
            "state": {
              "type": "file-explorer",
              "state": {
                "sortOrder": "alphabetical",
                "autoReveal": false
              },
              "icon": "lucide-folder-closed",
              "title": "Files"
            }
          },
          {
            "id": "f83ba44bd736f881",
            "type": "leaf",
            "state": {
              "type": "search",
              "state": {
                "query": "",
                "matchingCase": false,
                "explainSearch": false,
                "collapseAll": false,
                "extraContext": false,
                "sortOrder": "alphabetical"
              },
              "icon": "lucide-search",
              "title": "Search"
            }
          },
          {
            "id": "d9038e94a15138e6",
            "type": "leaf",
            "state": {
              "type": "bookmarks",
              "state": {},
              "icon": "lucide-bookmark",
              "title": "Bookmarks"
            }
          }
        ]
      }
    ],
    "direction": "horizontal",
    "width": 300
  },
  "right": {
    "id": "5401bcd454739bf7",
    "type": "split",
    "children": [
      {
        "id": "9d5bfb6f98a15e60",
        "type": "tabs",
        "children": [
          {
            "id": "1d0294e08bdf5eb3",
            "type": "leaf",
            "state": {
              "type": "backlink",
              "state": {
                "file": "20250623.md",
                "collapseAll": false,
                "extraContext": false,
                "sortOrder": "alphabetical",
                "showSearch": false,
                "searchQuery": "",
                "backlinkCollapsed": false,
                "unlinkedCollapsed": true
              },
              "icon": "links-coming-in",
              "title": "Backlinks for 20250623"
            }
          },
          {
            "id": "26cb71a8da170bdf",
            "type": "leaf",
            "state": {
              "type": "outgoing-link",
              "state": {
                "file": "20250623.md",
                "linksCollapsed": false,
                "unlinkedCollapsed": true
              },
              "icon": "links-going-out",
              "title": "Outgoing links from 20250623"
            }
          },
          {
            "id": "d284e06ec484369f",
            "type": "leaf",
            "state": {
              "type": "tag",
              "state": {
                "sortOrder": "frequency",
                "useHierarchy": true,
                "showSearch": false,
                "searchQuery": ""
              },
              "icon": "lucide-tags",
              "title": "Tags"
            }
          },
          {
            "id": "ef762890797002eb",
            "type": "leaf",
            "state": {
              "type": "outline",
              "state": {
                "file": "20250623.md",
                "followCursor": false,
                "showSearch": false,
                "searchQuery": ""
              },
              "icon": "lucide-list",
              "title": "Outline of 20250623"
            }
          }
        ]
      }
    ],
    "direction": "horizontal",
    "width": 300,
    "collapsed": true
  },
  "left-ribbon": {
    "hiddenItems": {
      "switcher:Open quick switcher": false,
      "graph:Open graph view": false,
      "canvas:Create new canvas": false,
      "daily-notes:Open today's daily note": false,
      "templates:Insert template": false,
      "command-palette:Open command palette": false
    }
  },
  "active": "5b4082abaec91411",
  "lastOpenFiles": [
    "20250625.md",
    "20250613.md",
    "20250623.md",
    "templates",
    "{{ year }}/{{ month }}/index.njk",
    "{{ year }}/index.njk",
    "{{ year }}/{{ month }}",
    "{{ year }}",
    "2025/6/index.njk",
    "2025/6",
    "2025/index.njk",
    "2025/20250623.md",
    "2025/20250613.md",
    "2025"
  ]
}